tune/__init__.py
tune/cli.py
tune/db_workers/__init__.py
tune/db_workers/dbmodels/__init__.py
tune/db_workers/dbmodels/base_model.py
tune/db_workers/dbmodels/models.py
tune/db_workers/tuning_client.py
tune/db_workers/tuning_server.py
tune/db_workers/utils.py
tune/io.py
tune/local.py
tune/plots.py
tune/priors.py
tune/summary.py
tune/utils.py
chess_tuning_tools-0.9.5.dist-info/LICENSE
chess_tuning_tools-0.9.5.dist-info/METADATA
chess_tuning_tools-0.9.5.dist-info/WHEEL
chess_tuning_tools-0.9.5.dist-info/entry_points.txt
chess_tuning_tools-0.9.5.dist-info/RECORD
