Metadata-Version: 2.1
Name: chess-tuning-tools
Version: 0.9.5
Summary: A collection of tools for local and distributed tuning of chess engines.
Home-page: https://github.com/kiudee/chess-tuning-tools
License: Apache-2.0
Keywords: chess,tuning,optimization,engine
Author: Karlson Pfannschmidt
Author-email: kiudee@mail.upb.de
Requires-Python: >=3.8,<3.10
Classifier: Development Status :: 3 - Alpha
Classifier: Intended Audience :: Developers
Classifier: License :: OSI Approved :: Apache Software License
Classifier: Natural Language :: English
Classifier: Programming Language :: Python :: 3
Classifier: Programming Language :: Python :: 3.8
Classifier: Programming Language :: Python :: 3.9
Provides-Extra: dist
Provides-Extra: docs
Requires-Dist: Click (>=7.1.2)
Requires-Dist: Sphinx (>=3) ; extra == "docs"
Requires-Dist: atomicwrites (>=1.4.0)
Requires-Dist: bask (>=0.9.3)
Requires-Dist: dill (>=0.3.4)
Requires-Dist: joblib (>=0.16.0) ; extra == "dist"
Requires-Dist: myst-nb (>=0.9) ; extra == "docs"
Requires-Dist: numpy (>=1.19.1,<1.24)
Requires-Dist: pandas (>=1.1.0) ; extra == "dist"
Requires-Dist: psycopg2 (>=2.8.5) ; extra == "dist"
Requires-Dist: scikit-learn (>=1,<2)
Requires-Dist: scikit-optimize (>=0.9,<0.10)
Requires-Dist: scipy (>=1.5.2)
Requires-Dist: sphinx-book-theme (>=0.0.35) ; extra == "docs"
Requires-Dist: sqlalchemy (>=1.3.18) ; extra == "dist"
Project-URL: Bug Tracker, https://github.com/kiudee/chess-tuning-tools/issues
Project-URL: Documentation, https://chess-tuning-tools.readthedocs.io
Project-URL: Repository, https://github.com/kiudee/chess-tuning-tools
